HISTORY.md
README.md
pyinaturalist_open_data/__init__.py
pyinaturalist_open_data/cli.py
pyinaturalist_open_data/constants.py
pyinaturalist_open_data/database.py
pyinaturalist_open_data/download.py
pyinaturalist_open_data/models/__init__.py
pyinaturalist_open_data/models/base.py
pyinaturalist_open_data/models/observation.py
pyinaturalist_open_data/models/photo.py
pyinaturalist_open_data/models/taxon.py
pyinaturalist_open_data/models/user.py
pyinaturalist_open_data/progress.py
pyinaturalist_open_data-0.1.1.dist-info/entry_points.txt
pyinaturalist_open_data-0.1.1.dist-info/LICENSE
pyinaturalist_open_data-0.1.1.dist-info/WHEEL
pyinaturalist_open_data-0.1.1.dist-info/METADATA
pyinaturalist_open_data-0.1.1.dist-info/RECORD
