Metadata-Version: 2.1
Name: pyinaturalist-open-data
Version: 0.1.1
Summary: Python utilities for working with inaturalist-open-data
Home-page: https://github.com/JWCook/pyinaturalist-open-data
License: MIT
Keywords: inaturalist,odp,observations,images
Author: Jordan Cook
Requires-Python: >=3.8,<4.0
Classifier: Development Status :: 3 - Alpha
Classifier: Environment :: Console
Classifier: License :: OSI Approved :: MIT License
Classifier: Programming Language :: Python :: 3
Classifier: Programming Language :: Python :: 3.8
Classifier: Programming Language :: Python :: 3.9
Classifier: Topic :: Software Development :: Libraries :: Python Modules
Requires-Dist: appdirs (>=1.4,<2.0)
Requires-Dist: boto3 (>=1.17,<2.0)
Requires-Dist: click (>=7.1,<7.2)
Requires-Dist: click-help-colors (>=0.9,<0.10)
Requires-Dist: pyinaturalist (>=0.12.0,<0.13.0)
Requires-Dist: requests-cache (>=0.6.3,<0.7.0)
Requires-Dist: rich (>=10.0)
Requires-Dist: sqlalchemy (>=1.4,<2.0)
Project-URL: Repository, https://github.com/JWCook/pyinaturalist-open-data
